[{"id":1,"title":"Titolo nr 1","description":"Descrizione nr 1","completed":true},{"id":2,"title":"Titolo","description":"Descrizione","completed":false},{"id":3,"title":"Titolo","description":"Descrizione","completed":false},{"id":4,"title":"Titolo","description":"Descrizione","completed":false},{"id":5,"title":"Titolo","description":"Descrizione","completed":false},{"id":7,"title":"Titolo","description":"Descrizione","completed":false},{"id":8,"title":"Titolo","description":"Descrizione","completed":false},{"id":9,"title":"Titolo","description":"Descrizione","completed":false},{"id":10,"title":"Titolo","description":"Descrizione","completed":false}]